{"fieldAliases": {"NAME": "NAME", "OBJECTID": "OBJECTID"}, "displayFieldName": "Name", "geometryType": "esriGeometryPoint", "features": [{"geometry": {"y": 30.23057671418605, "x": 120.42871426454695}, "attributes": {"NAME": "杭州萧山国际机场", "OBJECTID": 1}}, {"geometry": {"y": 30.273977694322753, "x": 120.20756860023721}, "attributes": {"NAME": "杭州汽车客运东站", "OBJECTID": 2}}, {"geometry": {"y": 30.235120320604178, "x": 120.18711822454655}, "attributes": {"NAME": "杭州汽车客运南站", "OBJECTID": 3}}, {"geometry": {"y": 30.26129742112425, "x": 120.09040038980747}, "attributes": {"NAME": "杭州汽车客运西站", "OBJECTID": 4}}, {"geometry": {"y": 30.317568080255565, "x": 120.11269972467785}, "attributes": {"NAME": "杭州汽车客运北站", "OBJECTID": 5}}, {"geometry": {"y": 30.28870746153927, "x": 120.2126796792098}, "attributes": {"NAME": "杭州火车东站", "OBJECTID": 6}}, {"geometry": {"y": 30.248863741184515, "x": 120.18597686717317}, "attributes": {"NAME": "杭州火车站", "OBJECTID": 7}}], "spatialReference": {"wkid": 2431}}